Workbook

Sheet Read Me
B1: Input Workshop for the Master Formula for Decision-Making
B2: The formula is only as good as its inputs. This workbook elicits them with established methods instead of raw guesses.
B4: This copy is pre-filled with the Campus Grounds worked example from the student guide, a student-run coffee cart deciding whether to lease a second location. Follow the guide cell by cell, and the Follow-along column on each tab shows the value you should see. When the walkthrough is done, replace the yellow cells with your own decision.
B6: Use the tabs in order, then carry the Summary values into the decision calculators.
B8: Tab 1, Probabilities. Anchors your prior in a base rate from similar past cases, converts a 10-to-90 range into a mean and standard deviation, and scores your past forecasts so you can see and correct overconfidence.
B9: Tab 2, Risk Tolerance. Turns two answerable questions about gambles into the risk tolerance R that the calculators use to price risk.
B10: Tab 3, Weights. Turns attribute rankings into defensible weights by the swing method, then scores up to five actions on up to six objectives at once.
B11: Tab 4, Likelihoods. Tests whether a signal is worth paying for by asking how often it would appear if the opposite were true.
B12: Tab 5, Summary. Collects the finished inputs in one place.
B14: Yellow cells are yours to change. Gold italic cells are the follow-along checks. Every other number is computed.

Sheet 1 Probabilities
B1: Calibrated Probabilities
B2: Pre-filled with Campus Grounds. Anchor the prior in a base rate, convert ranges to distributions, and score your forecasting record.
B4: A. Reference class: anchor the prior in a base rate | D4: Follow-along
B5: Similar past cases you can identify | C5: 12 | D5: 12 campus carts
B6: Cases where the outcome occurred | C6: 7 | D6: 7 profitable
B7: Base rate from the reference class | C7: =IF(C5>0,C6/C5,"") -> 0.58333333 | D7: 0.58
B8: Your prior for the current case | C8: 0.55 | D8: 0.55, reason written | E8: =IF(C9>0.25,"Your prior sits far from the base rate. That can be right, but it needs a stated reason. Write the reason down before you keep the number.","Your prior stays near the base rate. Adjust only for named differences between this case and the reference class.") -> Your prior stays near the base rate. Adjust only for named differences between this case and the reference class.
B9: Distance from the base rate | C9: =ABS(C8-C7) -> 0.033333333 | D9: 0.03
B11: B. Range to distribution: for continuous states such as daily cups | D11: Follow-along
B12: Low estimate, 1 chance in 10 it falls below | C12: 120 | D12: 120 cups | E12: These two cells feed the continuous calculators. If your 10-to-90 range feels easy to state, it is probably too narrow. Most people's ranges capture the truth far less than 80 percent of the time.
B13: High estimate, 1 chance in 10 it falls above | C13: 280 | D13: 280 cups
B14: Implied mean | C14: =(C12+C13)/2 -> 200 | D14: 200
B15: Implied standard deviation | C15: =(C13-C12)/2.5631 -> 62.424408 | D15: about 62
B17: C. Forecast log: score yourself and see your calibration
B18: Log real forecasts as you make them. Enter your probability and, when known, the outcome as 1 or 0. The sheet scores each with the Brier rule, where lower is better and 0.25 is the score of pure guessing.
B19: Forecast description | C19: Your p | D19: Outcome 0/1 | E19: Brier score
B20: Second cart clears 200 cups in week one | C20: 0.8 | D20: 1 | E20: =IF(AND(ISNUMBER(C20),ISNUMBER(D20)),(C20-D20)^2,"") -> 0.04
B21: Partner cafe signs by June | C21: 0.7 | D21: 0 | E21: =IF(AND(ISNUMBER(C21),ISNUMBER(D21)),(C21-D21)^2,"") -> 0.49
B22: Fall club funding renewed | C22: 0.9 | D22: 1 | E22: =IF(AND(ISNUMBER(C22),ISNUMBER(D22)),(C22-D22)^2,"") -> 0.01
B23: Homecoming pop-up sells out | C23: 0.6 | D23: 1 | E23: =IF(AND(ISNUMBER(C23),ISNUMBER(D23)),(C23-D23)^2,"") -> 0.16
B24: Bean supplier delivers on time | C24: 0.75 | D24: 0 | E24: =IF(AND(ISNUMBER(C24),ISNUMBER(D24)),(C24-D24)^2,"") -> 0.5625
E25: =IF(AND(ISNUMBER(C25),ISNUMBER(D25)),(C25-D25)^2,"")
E26: =IF(AND(ISNUMBER(C26),ISNUMBER(D26)),(C26-D26)^2,"")
E27: =IF(AND(ISNUMBER(C27),ISNUMBER(D27)),(C27-D27)^2,"")
E28: =IF(AND(ISNUMBER(C28),ISNUMBER(D28)),(C28-D28)^2,"")
E29: =IF(AND(ISNUMBER(C29),ISNUMBER(D29)),(C29-D29)^2,"")
E30: =IF(AND(ISNUMBER(C30),ISNUMBER(D30)),(C30-D30)^2,"")
E31: =IF(AND(ISNUMBER(C31),ISNUMBER(D31)),(C31-D31)^2,"")
E32: =IF(AND(ISNUMBER(C32),ISNUMBER(D32)),(C32-D32)^2,"")
E33: =IF(AND(ISNUMBER(C33),ISNUMBER(D33)),(C33-D33)^2,"")
E34: =IF(AND(ISNUMBER(C34),ISNUMBER(D34)),(C34-D34)^2,"")
E35: =IF(AND(ISNUMBER(C35),ISNUMBER(D35)),(C35-D35)^2,"")
E36: =IF(AND(ISNUMBER(C36),ISNUMBER(D36)),(C36-D36)^2,"")
... E39: =IF(AND(ISNUMBER(C39),ISNUMBER(D39)),(C39-D39)^2,"")
B41: Mean Brier score across resolved forecasts | C41: =IFERROR(AVERAGE(E20:E39),"") -> 0.2525 | D41: 0.253 on the seed rows | E41: =IF(C41="","",IF(C41<0.1,"Well calibrated so far.",IF(C41<0.2,"Reasonable. Watch the confident misses.","Your stated probabilities are running ahead of your accuracy. Pull confident forecasts toward the base rate."))) -> Your stated probabilities are running ahead of your accuracy. Pull confident forecasts toward the base rate.

Sheet 2 Risk Tolerance
B1: Risk Tolerance R
B2: Pre-filled with Campus Grounds, an 8,000 dollar treasury. Two answerable questions produce the R the calculators use.
B4: Method 1. The quick rule | D4: Follow-along
B5: Largest X where you would accept a 50/50 gamble of winning X or losing half of X | C5: 4000 | D5: $4,000, half the treasury | E5: Raise X until the gamble stops feeling acceptable. The largest acceptable X approximates your risk tolerance. This is the standard quick elicitation from decision analysis practice.
B6: Quick estimate of R | C6: =C5 -> 4000 | D6: $4,000
B8: Method 2. Refine with a certainty equivalent | D8: Follow-along
B9: A gamble pays this on a win | C9: 6000 | D9: the second cart, good state
B10: And this on a loss | C10: -3000 | D10: the second cart, bad state
B11: Probability of the win | C11: 0.7857 | D11: 0.79, the posterior
B12: The sure amount you would trade the gamble for | C12: 1855 | D12: $1,855
B13: Fitted risk tolerance R | C13: =INDEX(F21:F110,MATCH(MIN(H21:H110),H21:H110,0)) -> 3901.2393 | D13: about $4,000
B14: Expected value of that gamble, for reference | C14: =C11*C9+(1-C11)*C10 -> 4071.3 | D14: about $4,071
B16: =CONCATENATE("Consistency check. At the fitted R, a 50/50 gamble of +1,000 / −500 is worth the same as a sure ",TEXT(-C13*LN(0.5*EXP(-1000/C13)+0.5*EXP(500/C13)),"$#,##0"),". If that sure amount feels wrong, revisit the certainty equivalent above.") -> Consistency check. At the fitted R, a 50/50 gamble of +1,000 / −500 is worth the same as a sure $178. If that sure amount feels wrong, revisit the certainty equivalent above.
E20: R grid | F20: R | G20: CE at R | H20: |diff|
E21: 1 | F21: =MAX(ABS($C$9),ABS($C$10))*0.12*1.06^(E21-1) -> 720 | G21: =-F21*LN($C$11*EXP(-$C$9/F21)+(1-$C$11)*EXP(-$C$10/F21)) -> -1890.9374 | H21: =ABS(G21-$C$12) -> 3745.9374
E22: 2 | F22: =MAX(ABS($C$9),ABS($C$10))*0.12*1.06^(E22-1) -> 763.2 | G22: =-F22*LN($C$11*EXP(-$C$9/F22)+(1-$C$11)*EXP(-$C$10/F22)) -> -1824.4044 | H22: =ABS(G22-$C$12) -> 3679.4044
E23: 3 | F23: =MAX(ABS($C$9),ABS($C$10))*0.12*1.06^(E23-1) -> 808.992 | G23: =-F23*LN($C$11*EXP(-$C$9/F23)+(1-$C$11)*EXP(-$C$10/F23)) -> -1753.8899 | H23: =ABS(G23-$C$12) -> 3608.8899
E24: 4 | F24: =MAX(ABS($C$9),ABS($C$10))*0.12*1.06^(E24-1) -> 857.53152 | G24: =-F24*LN($C$11*EXP(-$C$9/F24)+(1-$C$11)*EXP(-$C$10/F24)) -> -1679.164 | H24: =ABS(G24-$C$12) -> 3534.164
E25: 5 | F25: =MAX(ABS($C$9),ABS($C$10))*0.12*1.06^(E25-1) -> 908.98341 | G25: =-F25*LN($C$11*EXP(-$C$9/F25)+(1-$C$11)*EXP(-$C$10/F25)) -> -1599.9886 | H25: =ABS(G25-$C$12) -> 3454.9886
E26: 6 | F26: =MAX(ABS($C$9),ABS($C$10))*0.12*1.06^(E26-1) -> 963.52242 | G26: =-F26*LN($C$11*EXP(-$C$9/F26)+(1-$C$11)*EXP(-$C$10/F26)) -> -1516.1209 | H26: =ABS(G26-$C$12) -> 3371.1209
E27: 7 | F27: =MAX(ABS($C$9),ABS($C$10))*0.12*1.06^(E27-1) -> 1021.3338 | G27: =-F27*LN($C$11*EXP(-$C$9/F27)+(1-$C$11)*EXP(-$C$10/F27)) -> -1427.3171 | H27: =ABS(G27-$C$12) -> 3282.3171
E28: 8 | F28: =MAX(ABS($C$9),ABS($C$10))*0.12*1.06^(E28-1) -> 1082.6138 | G28: =-F28*LN($C$11*EXP(-$C$9/F28)+(1-$C$11)*EXP(-$C$10/F28)) -> -1333.3382 | H28: =ABS(G28-$C$12) -> 3188.3382
E29: 9 | F29: =MAX(ABS($C$9),ABS($C$10))*0.12*1.06^(E29-1) -> 1147.5706 | G29: =-F29*LN($C$11*EXP(-$C$9/F29)+(1-$C$11)*EXP(-$C$10/F29)) -> -1233.9578 | H29: =ABS(G29-$C$12) -> 3088.9578
E30: 10 | F30: =MAX(ABS($C$9),ABS($C$10))*0.12*1.06^(E30-1) -> 1216.4249 | G30: =-F30*LN($C$11*EXP(-$C$9/F30)+(1-$C$11)*EXP(-$C$10/F30)) -> -1128.972 | H30: =ABS(G30-$C$12) -> 2983.972
E31: 11 | F31: =MAX(ABS($C$9),ABS($C$10))*0.12*1.06^(E31-1) -> 1289.4103 | G31: =-F31*LN($C$11*EXP(-$C$9/F31)+(1-$C$11)*EXP(-$C$10/F31)) -> -1018.2109 | H31: =ABS(G31-$C$12) -> 2873.2109
E32: 12 | F32: =MAX(ABS($C$9),ABS($C$10))*0.12*1.06^(E32-1) -> 1366.775 | G32: =-F32*LN($C$11*EXP(-$C$9/F32)+(1-$C$11)*EXP(-$C$10/F32)) -> -901.55296 | H32: =ABS(G32-$C$12) -> 2756.553
... E110: 90 | F110: =MAX(ABS($C$9),ABS($C$10))*0.12*1.06^(E110-1) -> 128692.88 | G110: =-F110*LN($C$11*EXP(-$C$9/F110)+(1-$C$11)*EXP(-$C$10/F110)) -> 4017.6064 | H110: =ABS(G110-$C$12) -> 2162.6064

Sheet 3 Weights
B1: Weights for Several Objectives at Once
B2: Pre-filled with Campus Grounds. Swing weighting turns worst-to-best comparisons into weights, then scores the actions.
B4: A. Attributes and swing ratings | H4: Follow-along | J4: B. Score the actions, 0 = worst level, 100 = best level
B5: Attribute | C5: Worst level in play | D5: Best level in play | E5: Swing rank | F5: Rating 0–100 | G5: Weight | J5: Action | K5: =IF($B$6="","—",$B$6) -> Net profit | L5: =IF($B$7="","—",$B$7) -> Student experience | M5: =IF($B$8="","—",$B$8) -> Volunteer workload | N5: =IF($B$9="","—",$B$9) -> — | O5: =IF($B$10="","—",$B$10) -> — | P5: =IF($B$11="","—",$B$11) -> — | Q5: Overall utility | R5: Follow-along
B6: Net profit | C6: −$3,000 | D6: +$6,000 | E6: 1 | F6: 100 | G6: =IF(ISNUMBER(F6),F6/SUM($F$6:$F$11),"") -> 0.5 | H6: 0.50 | J6: Second cart | K6: 85 | L6: 80 | M6: 30 | Q6: =IF($J6="","",IF(ISNUMBER(K6),K6*IF(ISNUMBER($G$6),$G$6,0),0)+IF(ISNUMBER(L6),L6*IF(ISNUMBER($G$7),$G$7,0),0)+IF(ISNUMBER(M6),M6*IF(ISNUMBER($G$8),$G$8,0),0)+IF(ISNUMBER(N6),N6*IF(ISNUMBER($G$9),$G$9,0),0)+IF(ISNUMBER(O6),O6*IF(ISNUMBER($G$10),$G$10,0),0)+IF(ISNUMBER(P6),P6*IF(ISNUMBER($G$11),$G$11,0),0)) -> 72.5 | R6: 72.5
B7: Student experience | C7: poor | D7: excellent | E7: 2 | F7: 60 | G7: =IF(ISNUMBER(F7),F7/SUM($F$6:$F$11),"") -> 0.3 | H7: 0.30 | J7: Partner with dining | K7: 55 | L7: 60 | M7: 80 | Q7: =IF($J7="","",IF(ISNUMBER(K7),K7*IF(ISNUMBER($G$6),$G$6,0),0)+IF(ISNUMBER(L7),L7*IF(ISNUMBER($G$7),$G$7,0),0)+IF(ISNUMBER(M7),M7*IF(ISNUMBER($G$8),$G$8,0),0)+IF(ISNUMBER(N7),N7*IF(ISNUMBER($G$9),$G$9,0),0)+IF(ISNUMBER(O7),O7*IF(ISNUMBER($G$10),$G$10,0),0)+IF(ISNUMBER(P7),P7*IF(ISNUMBER($G$11),$G$11,0),0)) -> 61.5 | R7: 61.5
B8: Volunteer workload | C8: heavy | D8: light | E8: 3 | F8: 40 | G8: =IF(ISNUMBER(F8),F8/SUM($F$6:$F$11),"") -> 0.2 | H8: 0.20 | J8: Hold | K8: 20 | L8: 40 | M8: 90 | Q8: =IF($J8="","",IF(ISNUMBER(K8),K8*IF(ISNUMBER($G$6),$G$6,0),0)+IF(ISNUMBER(L8),L8*IF(ISNUMBER($G$7),$G$7,0),0)+IF(ISNUMBER(M8),M8*IF(ISNUMBER($G$8),$G$8,0),0)+IF(ISNUMBER(N8),N8*IF(ISNUMBER($G$9),$G$9,0),0)+IF(ISNUMBER(O8),O8*IF(ISNUMBER($G$10),$G$10,0),0)+IF(ISNUMBER(P8),P8*IF(ISNUMBER($G$11),$G$11,0),0)) -> 40 | R8: 40.0
G9: =IF(ISNUMBER(F9),F9/SUM($F$6:$F$11),"") | Q9: =IF($J9="","",IF(ISNUMBER(K9),K9*IF(ISNUMBER($G$6),$G$6,0),0)+IF(ISNUMBER(L9),L9*IF(ISNUMBER($G$7),$G$7,0),0)+IF(ISNUMBER(M9),M9*IF(ISNUMBER($G$8),$G$8,0),0)+IF(ISNUMBER(N9),N9*IF(ISNUMBER($G$9),$G$9,0),0)+IF(ISNUMBER(O9),O9*IF(ISNUMBER($G$10),$G$10,0),0)+IF(ISNUMBER(P9),P9*IF(ISNUMBER($G$11),$G$11,0),0))
G10: =IF(ISNUMBER(F10),F10/SUM($F$6:$F$11),"") | Q10: =IF($J10="","",IF(ISNUMBER(K10),K10*IF(ISNUMBER($G$6),$G$6,0),0)+IF(ISNUMBER(L10),L10*IF(ISNUMBER($G$7),$G$7,0),0)+IF(ISNUMBER(M10),M10*IF(ISNUMBER($G$8),$G$8,0),0)+IF(ISNUMBER(N10),N10*IF(ISNUMBER($G$9),$G$9,0),0)+IF(ISNUMBER(O10),O10*IF(ISNUMBER($G$10),$G$10,0),0)+IF(ISNUMBER(P10),P10*IF(ISNUMBER($G$11),$G$11,0),0))
G11: =IF(ISNUMBER(F11),F11/SUM($F$6:$F$11),"")
J12: Best action on these objectives | Q12: =INDEX(J6:J10,MATCH(MAX(Q6:Q10),Q6:Q10,0)) -> Second cart | R12: Second cart
B13: How to rate. Give 100 to the attribute whose swing from worst to best matters most. Rate every other swing against it. A rating of 60 says that swing matters 60 percent as much as the top one. The rank column is only a discipline check on the ratings.
J14: This grid is the multi-attribute utility in working form. It scores several objectives at once instead of dollars alone. The weighted score plays the role of U in the master formula, and the probabilities still come from the other tabs.

Sheet 4 Likelihoods
B1: Is the Signal Worth Paying For
B2: Pre-filled with the Campus Grounds pop-up trial. A signal is useful only when its likelihood differs across the states.
B4: The two questions to ask of any report, survey, or study | D4: Follow-along
B5: How often would it fire if the state were TRUE, p(signal | true) | C5: 0.75 | D5: 0.75, from the cases | F5: =IF(C7="","",IF(C7<1.5,"Weak. This signal barely separates the states and will barely move your belief. Question whether it is worth its price.",IF(C7<3,"Moderate. The signal moves belief usefully. Compare its price against the value-of-information ceiling from Decision Two.","Informative. The signal separates the states well. Check the price against the value-of-information ceiling, then buy. For Campus Grounds the ceiling was 1,350 dollars and the trial cost 300, so the trial was bought."))) -> Informative. The signal separates the states well. Check the price against the value-of-information ceiling, then buy. For Campus Grounds the ceiling was 1,350 dollars and the trial cost 300, so the trial was bought.
B6: How often would it fire if the state were FALSE, p(signal | false) | C6: 0.25 | D6: 0.25
B7: Likelihood ratio | C7: =IF(C6>0,C5/C6,"") -> 3 | D7: 3.00, informative
B8: Your prior that the state is true | C8: 0.55 | D8: 0.55, from Tab 1
B9: Posterior if the signal fires | C9: =C8*C5/(C8*C5+(1-C8)*C6) -> 0.78571429 | D9: 0.79
B10: Posterior if the signal stays silent | C10: =C8*(1-C5)/(C8*(1-C5)+(1-C8)*(1-C6)) -> 0.28947368 | D10: 0.29

Sheet 5 Summary
B1: Finished Inputs, Ready for the Calculators
B2: Carry these values into the decision calculators. Each cell traces back to its elicitation tab.
B4: Input | C4: Value | D4: Follow-along | E4: Where it goes
B5: Prior probability, anchored in the reference class | C5: ='1 Probabilities'!C8 -> 0.55 | D5: 0.55 | E5: Paste into the prior cell of the two-state or three-state calculator.
B6: Mean of the continuous state | C6: ='1 Probabilities'!C14 -> 200 | D6: 200 | E6: Paste into the mean cell of the workbook-order calculator.
B7: Standard deviation of the continuous state | C7: ='1 Probabilities'!C15 -> 62.424408 | D7: about 62 | E7: Paste into the standard deviation cell of the same calculator.
B8: Risk tolerance R, fitted | C8: ='2 Risk Tolerance'!C13 -> 3901.2393 | D8: about $4,000 | E8: Paste into the risk tolerance cell of any calculator.
B9: Calibration score, mean Brier | C9: ='1 Probabilities'!C41 -> 0.2525 | D9: 0.253 on the seed rows | E9: Below 0.10 is well calibrated. Near 0.25 is guessing.
B10: Best action on several objectives | C10: ='3 Weights'!Q12 -> Second cart | D10: Second cart | E10: From the weighted multi-attribute grid.
B11: Likelihood ratio of the signal under test | C11: ='4 Likelihoods'!C7 -> 3 | D11: 3.00 | E11: Above 3 is informative. Below 1.5 is weak.
